Metadata-Version: 2.1
Name: nobi-flow-py-sdk
Version: 1.2.0
Summary: A python SKD for the flow blockchain
Home-page: https://github.com/nobbennob/nobi-flow-py-sdk-python3.8
Author: Janez Podhostnik
Author-email: janez.podhostnik@gmail.com
Maintainer: Abolfazl Bakiasay, Milad EbrahimKhani
Maintainer-email: abolfazl850@gmail.com, milade3013@gmail.com
Requires-Python: >=3.8,<4.0
License-File: LICENSE
Requires-Dist: betterproto[compiler] (<2.0.0,>=1.2.5)
Requires-Dist: ecdsa (>=v0.17.0)
Requires-Dist: phe (>=1.4.0)
Requires-Dist: grpcio-tools (<2.0.0,>=1.33.2)
Requires-Dist: grpclib (<0.5.0,>=0.4.1)
Requires-Dist: rlp (<3.0.0,>=2.0.1)
